uptimer/__init__.py
uptimer/client.py
uptimer/errors.py
uptimer/http.py
uptimer/py.typed
uptimer/endpoints/__init__.py
uptimer/endpoints/endpoint.py
uptimer/endpoints/regions.py
uptimer/endpoints/rules.py
uptimer/endpoints/v1.py
uptimer/endpoints/workspaces.py
uptimer/models/__init__.py
uptimer/models/deserialize.py
uptimer/models/errors.py
uptimer/models/region.py
uptimer/models/rule.py
uptimer/models/workspace.py
uptimer_python_sdk-0.3.0.dist-info/METADATA
uptimer_python_sdk-0.3.0.dist-info/WHEEL
uptimer_python_sdk-0.3.0.dist-info/licenses/LICENSE
uptimer_python_sdk-0.3.0.dist-info/licenses/NOTICE
uptimer_python_sdk-0.3.0.dist-info/RECORD
