Metadata-Version: 2.4
Name: uptimer-python-sdk
Version: 0.3.0
Summary: A Python SDK for uptimer
Project-URL: Repository, https://github.com/myuptime-info/uptimer-python-sdk
Author-email: Roman Zadoev <zadoev@gmail.com>
License: MIT
License-File: LICENSE
License-File: NOTICE
Requires-Python: >=3.9
Requires-Dist: httpx>=0.28.1
